nyanlang/__init__.py
nyanlang/helper.py
nyanlang/nyan.py
nyanlang/nyan.pyi
nyanlang-1.7.0.dist-info/LICENSE
nyanlang-1.7.0.dist-info/METADATA
nyanlang-1.7.0.dist-info/WHEEL
nyanlang-1.7.0.dist-info/entry_points.txt
nyanlang-1.7.0.dist-info/RECORD
