Metadata-Version: 2.1
Name: nyanlang
Version: 1.7.0
Summary: A Cutest Programming Language
Author: sserve-kr
Author-email: personal@sserve.me
Requires-Python: >=3.10,<4.0
Classifier: Programming Language :: Python :: 3
Classifier: Programming Language :: Python :: 3.10
Classifier: Programming Language :: Python :: 3.11
